# -----------------------------------------------------------------------------
# Opcode Maps (MCS Variant -> Standard)
# -----------------------------------------------------------------------------
from typing import Dict

OP_MAP_V1 = {
    0x00: 74,
    0x01: 15,
    0x02: 28,
    0x03: 56,
    0x04: 40,
    0x05: 41,
    0x06: 42,
    0x07: 43,
    0x08: 11,
    0x09: 24,
    0x0A: 9, # Not confirmed, set for remove garbage code
    0x0C: 25,
    0x0D: 66,
    0x0F: 82,
    0x10: 78,
    0x11: 85,
    0x12: 27,
    0x14: 50,
    0x15: 51,
    0x16: 52,
    0x17: 53,
    0x1A: 60,
    0x1B: 71,
    0x1C: 64,
    0x1D: 12,
    0x1E: 73,
    0x1F: 22,
    0x24: 19,
    0x25: 86,
    0x26: 81,
    0x27: 3,
    0x29: 75,
    0x2A: 26,
    0x2B: 54,
    0x2C: 25,
    0x2D: 79,
    0x2E: 63,
    0x2F: 77,
    0x30: 65,
    0x31: 5,
    0x32: 68,
    0x34: 72,
    0x35: 2,
    0x37: 89,
    0x38: 20,
    0x39: 87,
    0x3B: 83,
    0x3C: 80,
    0x3E: 84,
    0x3F: 23,
    0x40: 115,
    0x41: 88,
    0x43: 61,
    0x45: 64,
    0x46: 57,
    0x47: 30,
    0x48: 31,
    0x49: 32,
    0x4A: 33,
    0x4B: 62,
    0x4E: 76,
    0x4F: 60,
    0x50: 4,
    0x54: 10,
    0x56: 1,
    0x58: 55,
    0x5C: 71,
    0x5D: 100,
    0x5F: 122,
    0x64: 93,
    0x65: 143,
    0x66: 125,
    0x6B: 133,
    0x72: 90,
    0x74: 91,
    0x77: 131,
    0x7A: 102,
    0x7B: 134,
    0x82: 107,
    0x83: 146,
    0x86: 137,
    0x87: 106,
    0x8A: 92,
    0x8B: 109,
    0x8C: 95,
    0x90: 96,
    0x94: 108,
    0x96: 116,
    0x98: 126,
    0x99: 120,
    0x9E: 135,
    0xA0: 114,
    0xAD: 136,
    0xB3: 60,
    0xB7: 97,
    0xC0: 140,
    0xC1: 141,
    0xC2: 142,
    0xC5: 111,
    0xC6: 132,
    0xC7: 110,
    0xCA: 99,
    0xCC: 145,
    0xCF: 98,
    0xD2: 94,
    0xD3: 115,
    0xD4: 121,
    0xE2: 124,
    0xE6: 112,
    0xE7: 105,
    0xE8: 101,
    0xE9: 115,
    0xEA: 60,
    0xEB: 130,
    0xF0: 104,
    0xF3: 121,
    0xF7: 119,
    0xFA: 113,
    0xFC: 103
}

OP_MAP_V2 = {
    0x01: 83,
    0x02: 81,
    0x04: 62,
    0x05: 74,
    0x08: 30,
    0x09: 31,
    0x0A: 32,
    0x0B: 33,
    0x0C: 9,
    0x0E: 55,
    0x0F: 23,
    0x10: 11,
    0x12: 82,
    0x14: 75,
    0x15: 68,
    0x17: 2,
    0x1A: 24,
    0x1B: 106,
    0x1C: 63,
    0x1F: 66,
    0x20: 27,
    0x22: 4,
    0x23: 85,
    0x24: 87,
    0x25: 57,
    0x26: 54,
    0x28: 77,
    0x2A: 79,
    0x2B: 65,
    0x2C: 20,
    0x2D: 71,
    0x2E: 56,
    0x2F: 60,
    0x30: 71,
    0x31: 27,
    0x32: 12,
    0x33: 3,
    0x34: 71,
    0x35: 22,
    0x37: 89,
    0x38: 86,
    0x3C: 40,
    0x3D: 41,
    0x3E: 42,
    0x3F: 43,
    0x40: 28,
    0x43: 61,
    0x44: 1,
    0x45: 72,
    0x46: 26,
    0x47: 25,
    0x48: 56,
    0x49: 80,
    0x4A: 10,
    0x4C: 24,
    0x4D: 84,
    0x4E: 5,
    0x4F: 88,
    0x51: 19,
    0x54: 50,
    0x55: 51,
    0x56: 52,
    0x57: 53,
    0x58: 64,
    0x59: 76,
    0x5B: 73,
    0x5C: 78,
    0x5E: 137,
    0x61: 105,
    0x64: 110,
    0x66: 99,
    0x6E: 111,
    0x72: 145,
    0x74: 131,
    0x78: 121,
    0x82: 95,
    0x8B: 133,
    0x8D: 140,
    0x8E: 141,
    0x8F: 142,
    0x94: 110,
    0x95: 90,
    0x9E: 92,
    0xAC: 134,
    0xAF: 102,
    0xB0: 114,
    0xB9: 122,
    0xBC: 130,
    0xBE: 98,
    0xC0: 125,
    0xC2: 132,
    0xC4: 112,
    0xC6: 146,
    0xCA: 96,
    0xCC: 101,
    0xCD: 136,
    0xD1: 104,
    0xD2: 106,
    0xD4: 97,
    0xD5: 107,
    0xD6: 119,
    0xD9: 135,
    0xDB: 109,
    0xDC: 143,
    0xDD: 91,
    0xDF: 100,
    0xE5: 103,
    0xE8: 113,
    0xE9: 120,
    0xEB: 108,
    0xEE: 93,
    0xF4: 124,
    0xFD: 116,
    0xF2: 115,
    0xF3: 111,
    0xF7: 94,
}

OP_MAP_V3 = {
    0x00: 61,
    0x01: 9, # Not confirmed, set for remove garbage code
    0x02: 19,
    0x03: 82,
    0x04: 20,
    0x06: 65,
    0x08: 84,
    0x09: 11,
    0x0A: 26,
    0x0B: 25,
    0x0C: 50,
    0x0D: 51,
    0x0E: 52,
    0x0F: 53,
    0x10: 66,
    0x11: 28,
    0x14: 24,
    0x16: 62,
    0x18: 74,
    0x19: 86,
    0x1A: 78,
    0x1C: 40,
    0x1D: 41,
    0x1E: 42,
    0x1F: 43,
    0x29: 75,
    0x2A: 71,
    0x2B: 79,
    0x2D: 2,
    0x2E: 3,
    0x2F: 88,
    0x30: 27,
    0x31: 54,
    0x32: 1,
    0x34: 22,
    0x35: 72,
    0x36: 63,
    0x37: 12,
    0x3B: 68,
    0x3C: 83,
    0x3F: 80,
    0x43: 10,
    0x44: 76,
    0x45: 77,
    0x47: 81,
    0x48: 64,
    0x49: 57,
    0x4A: 87,
    0x4C: 73,
    0x4E: 23,
    0x50: 89,
    0x51: 56,
    0x52: 55,
    0x53: 4,
    0x55: 30,
    0x56: 31,
    0x57: 32,
    0x58: 33,
    0x5A: 60,
    0x60: 120,
    0x65: 107,
    0x67: 112,
    0x69: 134,
    0x6B: 98,
    0x6C: 122,
    0x6D: 103,
    0x6E: 94,
    0x72: 93,
    0x76: 119,
    0x77: 110,
    0x78: 95,
    0x7E: 131,
    0x88: 111,
    0x94: 137,
    0x97: 140,
    0x98: 141,
    0x99: 142,
    0x9B: 146,
    0x9E: 97,
    0xA9: 91,
    0xAC: 105,
    0xAD: 143,
    0xB2: 92,
    0xB7: 96,
    0xB9: 108,
    0xBE: 102,
    0xC0: 124,
    0xC7: 104,
    0xC8: 115,
    0xD3: 136,
    0xD4: 101,
    0xD6: 100,
    0xD7: 132,
    0xDB: 130,
    0xDE: 125,
    0xDF: 109,
    0xE0: 99,
    0xE4: 90,
    0xE7: 106,
    0xF1: 114,
    0xF4: 116,
    0xF6: 135,
    0xF7: 121,
    0xFE: 113
}

OP_MAP_V4 = {
    0x00: 9,
    0x01: 5,
    0x02: 76,
    0x03: 15,
    0x04: 40,
    0x05: 41,
    0x06: 42,
    0x07: 43,
    0x08: 25,
    0x09: 72,
    0x0A: 21,
    0x0B: 19,
    0x0D: 75,
    0x0E: 27,
    0x0F: 68,
    0x10: 56,
    0x11: 87,
    0x12: 86,
    0x13: 28,
    0x14: 54,
    0x15: 20,
    0x17: 71,
    0x18: 57,
    0x1A: 81,
    0x1B: 30,
    0x1C: 31,
    0x1D: 32,
    0x1E: 33,
    0x1F: 63,
    0x23: 60,
    0x27: 66,
    0x28: 88,
    0x29: 77,
    0x2A: 21,
    0x2B: 4,
    0x2C: 10,
    0x2E: 80,
    0x2F: 73,
    0x34: 3,
    0x35: 82,
    0x36: 24,
    0x3B: 62,
    0x3C: 78,
    0x3E: 50,
    0x3F: 51,
    0x40: 52,
    0x41: 53,
    0x43: 89,
    0x44: 79,
    0x46: 11,
    0x47: 24,
    0x48: 65,
    0x49: 23,
    0x4B: 22,
    0x4D: 55,
    0x4E: 66,
    0x4F: 85,
    0x50: 2,
    0x51: 83,
    0x52: 84,
    0x53: 1,
    0x56: 12,
    0x57: 26,
    0x58: 74,
    0x59: 61,
    0x5C: 64,
    0x60: 137,
    0x6B: 93,
    0x6E: 99,
    0x6F: 104,
    0x74: 122,
    0x79: 110,
    0x7B: 113,
    0x84: 101,
    0x85: 136,
    0x86: 97,
    0x87: 91,
    0x88: 116,
    0x89: 106,
    0x8C: 124,
    0x90: 131,
    0x9F: 125,
    0xA1: 105,
    0xA2: 126,
    0xA3: 109,
    0xA6: 134,
    0xA7: 119,
    0xAF: 103,
    0xB6: 130,
    0xBD: 146,
    0xC2: 143,
    0xC3: 111,
    0xC9: 90,
    0xD0: 120,
    0xD1: 121,
    0xD4: 95,
    0xD5: 112,
    0xD6: 135,
    0xD8: 94,
    0xDA: 114,
    0xDE: 100,
    0xDF: 147,
    0xE1: 96,
    0xE4: 107,
    0xE5: 102,
    0xE9: 140,
    0xEA: 141,
    0xEB: 142,
    0xF0: 98,
    0xF3: 115,
    0xF7: 132,
    0xFA: 108,
    0xFC: 133,
    0xFE: 92
}

STD_NAME_OP_MAP = {
    "STOP_CODE": 0,
    "POP_TOP": 1,
    "ROT_TWO": 2,
    "ROT_THREE": 3,
    "DUP_TOP": 4,
    "ROT_FOUR": 5,
    "NOP": 9,
    "UNARY_POSITIVE": 10,
    "UNARY_NEGATIVE": 11,
    "UNARY_NOT": 12,
    "UNARY_CONVERT": 13,
    "UNARY_INVERT": 15,
    "BINARY_POWER": 19,
    "BINARY_MULTIPLY": 20,
    "BINARY_DIVIDE": 21,
    "BINARY_MODULO": 22,
    "BINARY_ADD": 23,
    "BINARY_SUBTRACT": 24,
    "BINARY_SUBSCR": 25,
    "BINARY_FLOOR_DIVIDE": 26,
    "BINARY_TRUE_DIVIDE": 27,
    "INPLACE_FLOOR_DIVIDE": 28,
    "INPLACE_TRUE_DIVIDE": 29,
    "SLICE+0": 30,
    "SLICE+1": 31,
    "SLICE+2": 32,
    "SLICE+3": 33,
    "STORE_SLICE+0": 40,
    "STORE_SLICE+1": 41,
    "STORE_SLICE+2": 42,
    "STORE_SLICE+3": 43,
    "DELETE_SLICE+0": 50,
    "DELETE_SLICE+1": 51,
    "DELETE_SLICE+2": 52,
    "DELETE_SLICE+3": 53,
    "STORE_MAP": 54,
    "INPLACE_ADD": 55,
    "INPLACE_SUBTRACT": 56,
    "INPLACE_MULTIPLY": 57,
    "INPLACE_DIVIDE": 58,
    "INPLACE_MODULO": 59,
    "STORE_SUBSCR": 60,
    "DELETE_SUBSCR": 61,
    "BINARY_LSHIFT": 62,
    "BINARY_RSHIFT": 63,
    "BINARY_AND": 64,
    "BINARY_XOR": 65,
    "BINARY_OR": 66,
    "INPLACE_POWER": 67,
    "GET_ITER": 68,
    "PRINT_EXPR": 70,
    "PRINT_ITEM": 71,
    "PRINT_NEWLINE": 72,
    "PRINT_ITEM_TO": 73,
    "PRINT_NEWLINE_TO": 74,
    "INPLACE_LSHIFT": 75,
    "INPLACE_RSHIFT": 76,
    "INPLACE_AND": 77,
    "INPLACE_XOR": 78,
    "INPLACE_OR": 79,
    "BREAK_LOOP": 80,
    "WITH_CLEANUP": 81,
    "LOAD_LOCALS": 82,
    "RETURN_VALUE": 83,
    "IMPORT_STAR": 84,
    "EXEC_STMT": 85,
    "YIELD_VALUE": 86,
    "POP_BLOCK": 87,
    "END_FINALLY": 88,
    "BUILD_CLASS": 89,
    "STORE_NAME": 90,
    "DELETE_NAME": 91,
    "UNPACK_SEQUENCE": 92,
    "FOR_ITER": 93,
    "LIST_APPEND": 94,
    "STORE_ATTR": 95,
    "DELETE_ATTR": 96,
    "STORE_GLOBAL": 97,
    "DELETE_GLOBAL": 98,
    "DUP_TOPX": 99,
    "LOAD_CONST": 100,
    "LOAD_NAME": 101,
    "BUILD_TUPLE": 102,
    "BUILD_LIST": 103,
    "BUILD_SET": 104,
    "BUILD_MAP": 105,
    "LOAD_ATTR": 106,
    "COMPARE_OP": 107,
    "IMPORT_NAME": 108,
    "IMPORT_FROM": 109,
    "JUMP_FORWARD": 110,
    "JUMP_IF_FALSE_OR_POP": 111,
    "JUMP_IF_TRUE_OR_POP": 112,
    "JUMP_ABSOLUTE": 113,
    "POP_JUMP_IF_FALSE": 114,
    "POP_JUMP_IF_TRUE": 115,
    "LOAD_GLOBAL": 116,
    "CONTINUE_LOOP": 119,
    "SETUP_LOOP": 120,
    "SETUP_EXCEPT": 121,
    "SETUP_FINALLY": 122,
    "LOAD_FAST": 124,
    "STORE_FAST": 125,
    "DELETE_FAST": 126,
    "RAISE_VARARGS": 130,
    "CALL_FUNCTION": 131,
    "MAKE_FUNCTION": 132,
    "BUILD_SLICE": 133,
    "MAKE_CLOSURE": 134,
    "LOAD_CLOSURE": 135,
    "LOAD_DEREF": 136,
    "STORE_DEREF": 137,
    "CALL_FUNCTION_VAR": 140,
    "CALL_FUNCTION_KW": 141,
    "CALL_FUNCTION_VAR_KW": 142,
    "SETUP_WITH": 143,
    "EXTENDED_ARG": 145,
    "SET_ADD": 146,
    "MAP_ADD": 147
}

MAP_STORE = {
    1: OP_MAP_V1,
    2: OP_MAP_V2,
    3: OP_MAP_V3,
    4: OP_MAP_V4
}


def get_mcs2std_op_map(version: int) -> Dict[bytes, int]:
    if version < 0:
        version = 1
    if version in MAP_STORE:
        return MAP_STORE[version]
    else:
        return OP_MAP_V1

def get_std2mcs_op_map(version: int) -> Dict[bytes, int]:
    if version < 0:
        version = 1
    if -version in MAP_STORE:
        return MAP_STORE[-version]
    mcs2std = get_mcs2std_op_map(version)
    MAP_STORE[-version] = {std_op: mcs_op for mcs_op, std_op in mcs2std.items()}
    return MAP_STORE[-version]

def get_mcs_name_op_map(version: int) -> Dict[str, int]:
    if version < 0:
        version = 1
    map_idx = -100 - version
    if map_idx in MAP_STORE:
        return MAP_STORE[map_idx]
    std2mcs = get_std2mcs_op_map(version)
    MAP_STORE[map_idx] = STD_NAME_OP_MAP.copy()
    for name, std_op in STD_NAME_OP_MAP.items():
        mcs_op = std2mcs.get(std_op)
        if mcs_op is not None:
            MAP_STORE[map_idx][name] = mcs_op
    return MAP_STORE[map_idx]